metarna/__init__.py
metarna/pymiranda.cpython-36m-darwin.so
metarna/report.py
metarna/target_scan.py
metarna-4.0.5.dist-info/DESCRIPTION.rst
metarna-4.0.5.dist-info/METADATA
metarna-4.0.5.dist-info/RECORD
metarna-4.0.5.dist-info/WHEEL
metarna-4.0.5.dist-info/metadata.json
metarna-4.0.5.dist-info/top_level.txt
