Metadata-Version: 2.0
Name: metarna
Version: 4.0.5
Summary: Finds target sites for the miRNAs in genomic sequences.
Home-page: https://github.com/prashnts/metarna
Author: Prashant Sinha
Author-email: prashant@ducic.ac.in
License: GPLv3
Platform: UNKNOWN
Classifier: Development Status :: 4 - Beta
Classifier: Intended Audience :: Developers
Classifier: Intended Audience :: Science/Research
Classifier: License :: OSI Approved :: GNU General Public License v3 (GPLv3)
Classifier: Programming Language :: Python
Classifier: Programming Language :: Python :: 2
Classifier: Programming Language :: Python :: 3
Classifier: Topic :: Scientific/Engineering :: Bio-Informatics
